jupyter_locuszoom/__init__.py
jupyter_locuszoom/_frontend.py
jupyter_locuszoom/_version.py
jupyter_locuszoom/locus_zoom.py
jupyter_locuszoom/labextension/build_log.json
jupyter_locuszoom/labextension/package.json
jupyter_locuszoom/labextension/static/lib_index_js.1462f2843f4c04a52881.js
jupyter_locuszoom/labextension/static/lib_index_js.1462f2843f4c04a52881.js.map
jupyter_locuszoom/labextension/static/lib_plugin_js.7e633c522b2189389736.js
jupyter_locuszoom/labextension/static/lib_plugin_js.7e633c522b2189389736.js.map
jupyter_locuszoom/labextension/static/lib_widget_js.751b11392fdca570e288.js
jupyter_locuszoom/labextension/static/lib_widget_js.751b11392fdca570e288.js.map
jupyter_locuszoom/labextension/static/lib_widget_js.b631ee8a6ff24aede47c.js
jupyter_locuszoom/labextension/static/lib_widget_js.b631ee8a6ff24aede47c.js.map
jupyter_locuszoom/labextension/static/lib_widget_js.d278f1d07325a0e4e5cb.js
jupyter_locuszoom/labextension/static/lib_widget_js.d278f1d07325a0e4e5cb.js.map
jupyter_locuszoom/labextension/static/lib_widget_js.dc6697cf94dcc4cb14bc.js
jupyter_locuszoom/labextension/static/lib_widget_js.dc6697cf94dcc4cb14bc.js.map
jupyter_locuszoom/labextension/static/lib_widget_js.e00d9776199cdb3b0918.js
jupyter_locuszoom/labextension/static/lib_widget_js.e00d9776199cdb3b0918.js.map
jupyter_locuszoom/labextension/static/lib_widget_js.ff0b505f89816ef2fa6c.js
jupyter_locuszoom/labextension/static/lib_widget_js.ff0b505f89816ef2fa6c.js.map
jupyter_locuszoom/labextension/static/lib_widget_js.ff612b296119c6362583.js
jupyter_locuszoom/labextension/static/lib_widget_js.ff612b296119c6362583.js.map
jupyter_locuszoom/labextension/static/remoteEntry.03af74c81e37b8d85832.js
jupyter_locuszoom/labextension/static/remoteEntry.03af74c81e37b8d85832.js.map
jupyter_locuszoom/labextension/static/remoteEntry.32f59f51d40bf5ffa01e.js.map
jupyter_locuszoom/labextension/static/remoteEntry.35a953c4bbbdf71b3939.js.map
jupyter_locuszoom-0.1.1.dev0.dist-info/METADATA
jupyter_locuszoom-0.1.1.dev0.dist-info/WHEEL
jupyter_locuszoom-0.1.1.dev0.dist-info/licenses/LICENSE.txt
jupyter_locuszoom-0.1.1.dev0.dist-info/RECORD
